{"Added":[{"Id":63151,"Kind":16,"Name":"AccountantAct","PackagePath":"/src/Page-Ext/PageExt%2063151%20-%20Accountant%20RC.al"},{"Id":63107,"Kind":12,"Name":"Released Journal","PackagePath":"/src/Page/Page%2063107-Cue%20Released%20Journal.al"},{"Id":63152,"Kind":16,"Name":"BusinessManagerRC","PackagePath":"/src/Page-Ext/PageExt%2063152%20-%20Business%20Manager%20RC.al"}],"Modified":[{"Id":63109,"Kind":13,"Name":"Detail Trial Balance Custome","PackagePath":"/src/Report/Report%2063109%20-%20Detail%20Trial%20Balance%20Custome.al"}],"Removed":[]}